MANIFEST.in
README.txt
setup.py
docs/CHANGELOG.txt
docs/LICENSE.txt
docs/PC09-LighningTalk-cornerstone-soup.pdf
src/cornerstone/__init__.py
src/cornerstone.soup.egg-info/PKG-INFO
src/cornerstone.soup.egg-info/SOURCES.txt
src/cornerstone.soup.egg-info/dependency_links.txt
src/cornerstone.soup.egg-info/namespace_packages.txt
src/cornerstone.soup.egg-info/not-zip-safe
src/cornerstone.soup.egg-info/requires.txt
src/cornerstone.soup.egg-info/top_level.txt
src/cornerstone/soup/__init__.py
src/cornerstone/soup/configure.zcml
src/cornerstone/soup/soup.py
src/cornerstone/soup/soup.txt
src/cornerstone/soup/ting.py
src/cornerstone/soup/ting.txt
src/cornerstone/soup/browser/__init__.py
src/cornerstone/soup/browser/admin.pt
src/cornerstone/soup/browser/configure.zcml
src/cornerstone/soup/browser/controlpanel.pt
src/cornerstone/soup/browser/soup_icon.gif
src/cornerstone/soup/browser/soupadministration.pt
src/cornerstone/soup/browser/views.py
src/cornerstone/soup/interfaces/__init__.py
src/cornerstone/soup/interfaces/soup.py
src/cornerstone/soup/interfaces/ting.py
src/cornerstone/soup/profile/actionicons.xml
src/cornerstone/soup/profile/controlpanel.xml
src/cornerstone/soup/profile/metadata.xml
src/cornerstone/soup/tests/__init__.py
src/cornerstone/soup/tests/configure.zcml
src/cornerstone/soup/tests/env.py
src/cornerstone/soup/tests/test_soup.py