Metadata-Version: 1.1
Name: cornerstone.soup
Version: 2.4.1.1
Summary: Container with queryable Records for Zope 2
Home-page: http://dev.plone.org/collective/browser/cornerstone.soup
Author: BlueDynamics Alliance
Author-email: dev@bluedynamics.com
License: BSD
Keywords: container data record catalog txng3
Platform: UNKNOWN
Classifier: Development Status :: 5 - Production/Stable
Classifier: License :: OSI Approved :: BSD License
Classifier: Operating System :: OS Independent
Classifier: Programming Language :: Python
Classifier: Framework :: Zope2
Classifier: Intended Audience :: Developers
Classifier: Topic :: Software Development :: Libraries :: Python Modules
